{
	"Description": "0 length Extension",
	"SendNtpv5Data": {
		"LI": 0,
		"VN": 5,
		"Mode": 3,
		"Stratum": 0,
		"Poll": 0,
		"Precision": 0,
		"Timescale": 0,
		"Era": 0,
		"Flags": 0,
		"RootDelay": 0,
		"RootDisperasion": 0,
		"ServerCookie": 0,
		"ClientCookie": 1234,
		"ReceiveTimestamp": 0,
		"TransmitTimestamp": 0,
		"ReferenceIDsRequestEx": {
			"Length": 16,
			"Offset": 0
		},
		"DraftIdentificationEx": {
			"Length": 24,
			"Draft": "draft-ietf-ntp-ntpv5-00 "
		}
	},
	"ForTestOverwriteBuffer" :[
		{"Index":51, "Value":0}
	],
	"ResponseTimeout": true
}
